cocoa/__init__.py
cocoa/constants.py
cocoa/evaluate_repo.py
cocoa/linting.py
cocoa/notebooks.py
cocoa/repo.py
dsi_cocoa-0.5.9.dist-info/METADATA
dsi_cocoa-0.5.9.dist-info/WHEEL
dsi_cocoa-0.5.9.dist-info/entry_points.txt
dsi_cocoa-0.5.9.dist-info/top_level.txt
dsi_cocoa-0.5.9.dist-info/RECORD
