Metadata-Version: 2.1
Name: dsi-cocoa
Version: 0.5.9
Summary: Clinic Opinionated Codebase Oversight and Analysis
Author-email: Nick Ross <tspread@uchicago.edu>, Trevor Spreadbury <tspread@uchicago.edu>
Maintainer: Nick Ross, Trevor Spreadbury
Keywords: codebase analysis,uchicago dsi
Classifier: Programming Language :: Python :: 3
Classifier: Operating System :: OS Independent
Requires-Python: >=3.10
Requires-Dist: GitPython
Requires-Dist: nbconvert
Requires-Dist: ipython
Requires-Dist: termcolor
Requires-Dist: requests
Requires-Dist: ruff
